{
  "metadata": {
    "start_date": "2025-08-12",
    "end_date": "2026-12-31",
    "starting_balance": 8000,
    "final_balance": 8093.900027509068,
    "total_bank_balance": 8000,
    "bank_count": 2
  },
  "balance_data": [
    {
      "date": "2025-08-12",
      "balance": 8000
    },
    {
      "date": "2025-09-01",
      "balance": 8009.27130411543
    },
    {
      "date": "2025-10-01",
      "balance": 8018.5687789160165
    },
    {
      "date": "2025-11-01",
      "balance": 8027.892501547898
    },
    {
      "date": "2025-12-01",
      "balance": 8037.24254938491
    },
    {
      "date": "2026-01-01",
      "balance": 8046.6190000292545
    },
    {
      "date": "2026-02-01",
      "balance": 8056.021931312181
    },
    {
      "date": "2026-03-01",
      "balance": 8065.451421294655
    },
    {
      "date": "2026-04-01",
      "balance": 8074.907548268041
    },
    {
      "date": "2026-05-01",
      "balance": 8084.390390754778
    },
    {
      "date": "2026-06-01",
      "balance": 8093.900027509068
    }
  ],
  "transactions": [
    {
      "date": "2025-09-01",
      "name": "BOK Savings Interest",
      "amount": 0.41647581636605757,
      "balance": 8000.416475816366,
      "type": "income"
    },
    {
      "date": "2025-09-01",
      "name": "Capital One 360 Interest",
      "amount": 8.854828299064588,
      "balance": 8009.27130411543,
      "type": "income"
    },
    {
      "date": "2025-10-01",
      "name": "BOK Savings Interest",
      "amount": 0.4165105067871811,
      "balance": 8009.687814622217,
      "type": "income"
    },
    {
      "date": "2025-10-01",
      "name": "Capital One 360 Interest",
      "amount": 8.880964293799893,
      "balance": 8018.5687789160165,
      "type": "income"
    },
    {
      "date": "2025-11-01",
      "name": "BOK Savings Interest",
      "amount": 0.41654520009784896,
      "balance": 8018.9853241161145,
      "type": "income"
    },
    {
      "date": "2025-11-01",
      "name": "Capital One 360 Interest",
      "amount": 8.9071774317838,
      "balance": 8027.892501547898,
      "type": "income"
    },
    {
      "date": "2025-12-01",
      "name": "BOK Savings Interest",
      "amount": 0.4165798962983018,
      "balance": 8028.309081444197,
      "type": "income"
    },
    {
      "date": "2025-12-01",
      "name": "Capital One 360 Interest",
      "amount": 8.93346794071305,
      "balance": 8037.24254938491,
      "type": "income"
    },
    {
      "date": "2026-01-01",
      "name": "BOK Savings Interest",
      "amount": 0.4166145953887803,
      "balance": 8037.659163980298,
      "type": "income"
    },
    {
      "date": "2026-01-01",
      "name": "Capital One 360 Interest",
      "amount": 8.959836048956454,
      "balance": 8046.6190000292545,
      "type": "income"
    },
    {
      "date": "2026-02-01",
      "name": "BOK Savings Interest",
      "amount": 0.4166492973695252,
      "balance": 8047.035649326624,
      "type": "income"
    },
    {
      "date": "2026-02-01",
      "name": "Capital One 360 Interest",
      "amount": 8.986281985556879,
      "balance": 8056.021931312181,
      "type": "income"
    },
    {
      "date": "2026-03-01",
      "name": "BOK Savings Interest",
      "amount": 0.41668400224077723,
      "balance": 8056.438615314421,
      "type": "income"
    },
    {
      "date": "2026-03-01",
      "name": "Capital One 360 Interest",
      "amount": 9.01280598023324,
      "balance": 8065.451421294655,
      "type": "income"
    },
    {
      "date": "2026-04-01",
      "name": "BOK Savings Interest",
      "amount": 0.4167187100027772,
      "balance": 8065.868140004658,
      "type": "income"
    },
    {
      "date": "2026-04-01",
      "name": "Capital One 360 Interest",
      "amount": 9.03940826338249,
      "balance": 8074.907548268041,
      "type": "income"
    },
    {
      "date": "2026-05-01",
      "name": "BOK Savings Interest",
      "amount": 0.4167534206557659,
      "balance": 8075.324301688696,
      "type": "income"
    },
    {
      "date": "2026-05-01",
      "name": "Capital One 360 Interest",
      "amount": 9.066089066081624,
      "balance": 8084.390390754778,
      "type": "income"
    },
    {
      "date": "2026-06-01",
      "name": "BOK Savings Interest",
      "amount": 0.41678813419998406,
      "balance": 8084.807178888978,
      "type": "income"
    },
    {
      "date": "2026-06-01",
      "name": "Capital One 360 Interest",
      "amount": 9.092848620089683,
      "balance": 8093.900027509068,
      "type": "income"
    }
  ],
  "bank_data": [
    {
      "date": "2025-09-01",
      "bank": "BOK Savings",
      "balance": 5000.416475816366,
      "interest_rate": 0.001,
      "interest_type": "compound",
      "monthly_interest": 0.41647581636605757
    },
    {
      "date": "2025-09-01",
      "bank": "Capital One 360",
      "balance": 3008.8548282990646,
      "interest_rate": 0.036,
      "interest_type": "compound",
      "monthly_interest": 8.854828299064588
    },
    {
      "date": "2025-10-01",
      "bank": "BOK Savings",
      "balance": 5000.832986323153,
      "interest_rate": 0.001,
      "interest_type": "compound",
      "monthly_interest": 0.4165105067871811
    },
    {
      "date": "2025-10-01",
      "bank": "Capital One 360",
      "balance": 3017.7357925928645,
      "interest_rate": 0.036,
      "interest_type": "compound",
      "monthly_interest": 8.880964293799893
    },
    {
      "date": "2025-11-01",
      "bank": "BOK Savings",
      "balance": 5001.249531523251,
      "interest_rate": 0.001,
      "interest_type": "compound",
      "monthly_interest": 0.41654520009784896
    },
    {
      "date": "2025-11-01",
      "bank": "Capital One 360",
      "balance": 3026.6429700246485,
      "interest_rate": 0.036,
      "interest_type": "compound",
      "monthly_interest": 8.9071774317838
    },
    {
      "date": "2025-12-01",
      "bank": "BOK Savings",
      "balance": 5001.666111419549,
      "interest_rate": 0.001,
      "interest_type": "compound",
      "monthly_interest": 0.4165798962983018
    },
    {
      "date": "2025-12-01",
      "bank": "Capital One 360",
      "balance": 3035.5764379653615,
      "interest_rate": 0.036,
      "interest_type": "compound",
      "monthly_interest": 8.93346794071305
    },
    {
      "date": "2026-01-01",
      "bank": "BOK Savings",
      "balance": 5002.082726014938,
      "interest_rate": 0.001,
      "interest_type": "compound",
      "monthly_interest": 0.4166145953887803
    },
    {
      "date": "2026-01-01",
      "bank": "Capital One 360",
      "balance": 3044.5362740143178,
      "interest_rate": 0.036,
      "interest_type": "compound",
      "monthly_interest": 8.959836048956454
    },
    {
      "date": "2026-02-01",
      "bank": "BOK Savings",
      "balance": 5002.499375312307,
      "interest_rate": 0.001,
      "interest_type": "compound",
      "monthly_interest": 0.4166492973695252
    },
    {
      "date": "2026-02-01",
      "bank": "Capital One 360",
      "balance": 3053.522555999875,
      "interest_rate": 0.036,
      "interest_type": "compound",
      "monthly_interest": 8.986281985556879
    },
    {
      "date": "2026-03-01",
      "bank": "BOK Savings",
      "balance": 5002.916059314548,
      "interest_rate": 0.001,
      "interest_type": "compound",
      "monthly_interest": 0.41668400224077723
    },
    {
      "date": "2026-03-01",
      "bank": "Capital One 360",
      "balance": 3062.535361980108,
      "interest_rate": 0.036,
      "interest_type": "compound",
      "monthly_interest": 9.01280598023324
    },
    {
      "date": "2026-04-01",
      "bank": "BOK Savings",
      "balance": 5003.332778024551,
      "interest_rate": 0.001,
      "interest_type": "compound",
      "monthly_interest": 0.4167187100027772
    },
    {
      "date": "2026-04-01",
      "bank": "Capital One 360",
      "balance": 3071.5747702434905,
      "interest_rate": 0.036,
      "interest_type": "compound",
      "monthly_interest": 9.03940826338249
    },
    {
      "date": "2026-05-01",
      "bank": "BOK Savings",
      "balance": 5003.749531445206,
      "interest_rate": 0.001,
      "interest_type": "compound",
      "monthly_interest": 0.4167534206557659
    },
    {
      "date": "2026-05-01",
      "bank": "Capital One 360",
      "balance": 3080.640859309572,
      "interest_rate": 0.036,
      "interest_type": "compound",
      "monthly_interest": 9.066089066081624
    },
    {
      "date": "2026-06-01",
      "bank": "BOK Savings",
      "balance": 5004.166319579406,
      "interest_rate": 0.001,
      "interest_type": "compound",
      "monthly_interest": 0.41678813419998406
    },
    {
      "date": "2026-06-01",
      "bank": "Capital One 360",
      "balance": 3089.7337079296617,
      "interest_rate": 0.036,
      "interest_type": "compound",
      "monthly_interest": 9.092848620089683
    }
  ],
  "budget": [
    {
      "id": 1754663371828,
      "name": "Gas",
      "amount": -120,
      "type": "expense",
      "startDate": "2025-08-08",
      "endDate": null,
      "linkedBankId": "419531"
    },
    {
      "id": 1754665171678,
      "name": "Income",
      "amount": 222.22,
      "type": "income",
      "startDate": "2025-08-08",
      "endDate": "2026-05-01",
      "linkedBankId": "422402"
    },
    {
      "id": 1754665203999,
      "name": "Food",
      "amount": -15,
      "type": "expense",
      "startDate": "2025-08-08",
      "endDate": null,
      "linkedBankId": "419531"
    },
    {
      "id": 1754665212431,
      "name": "Dates",
      "amount": -50,
      "type": "expense",
      "startDate": "2025-08-08",
      "endDate": null,
      "linkedBankId": "419531"
    },
    {
      "id": 1754665222063,
      "name": "Insurance",
      "amount": -90,
      "type": "expense",
      "startDate": "2025-08-08",
      "endDate": null,
      "linkedBankId": "419531"
    },
    {
      "id": 1754665229239,
      "name": "Social",
      "amount": -15,
      "type": "expense",
      "startDate": "2025-08-08",
      "endDate": null,
      "linkedBankId": "419531"
    },
    {
      "id": 1754665841852,
      "name": "Carnegie Hall",
      "amount": -291,
      "type": "expense",
      "startDate": "2025-08-08",
      "endDate": "2026-05-01",
      "linkedBankId": null
    },
    {
      "id": 1754665888260,
      "name": "School Tuition",
      "amount": -364,
      "type": "expense",
      "startDate": "2025-08-08",
      "endDate": "2026-05-01",
      "linkedBankId": null
    },
    {
      "id": 1754665978349,
      "name": "World Cup",
      "amount": -136,
      "type": "expense",
      "startDate": "2025-08-08",
      "endDate": "2026-06-01"
    },
    {
      "id": 1754666057223,
      "name": "College Fund",
      "amount": 100,
      "type": "income",
      "startDate": "2025-08-08",
      "endDate": "2026-05-01"
    },
    {
      "id": 1755017220590,
      "name": "BOK Savings Interest",
      "amount": 0.4168228506356726,
      "type": "income",
      "startDate": "2025-08-12",
      "endDate": null,
      "isAutoGenerated": true,
      "linkedBankId": 503958
    },
    {
      "id": 1755016720536,
      "name": "Capital One 360 Interest",
      "amount": 9.119687157849777,
      "type": "income",
      "startDate": "2025-08-12",
      "endDate": null,
      "isAutoGenerated": true,
      "linkedBankId": 3904
    }
  ],
  "banks": [
    {
      "id": 1754694339566,
      "name": "BOK Savings Interest",
      "amount": 0,
      "type": "income",
      "startDate": "2025-08-08",
      "endDate": null,
      "isAutoGenerated": true,
      "linkedBankId": 419531,
      "interestType": "compound",
      "metadata": {
        "createdBy": "bank_system",
        "createdAt": "2025-08-08T23:05:39.327Z",
        "principalAmount": 4000,
        "annualRate": 0,
        "updatedAt": "2025-08-09T16:31:30.448Z"
      }
    },
    {
      "id": 1754694339396,
      "name": "Capital One 360 Interest",
      "amount": 11.973342429114005,
      "type": "income",
      "startDate": "2025-08-08",
      "endDate": null,
      "isAutoGenerated": true,
      "linkedBankId": 422402,
      "interestType": "compound",
      "metadata": {
        "createdBy": "bank_system",
        "createdAt": "2025-08-08T23:05:39.327Z",
        "principalAmount": 5020,
        "annualRate": 0.028999999999999998,
        "updatedAt": "2025-08-08T23:30:25.929Z"
      }
    }
  ]
}